objectsyncer/__init__.py
objectsyncer/admin.py
objectsyncer/apps.py
objectsyncer/models.py
objectsyncer/tests.py
objectsyncer/utils_cli.py
objectsyncer/utils_srv.py
objectsyncer/views.py
objectsyncer/management/__init__.py
objectsyncer/management/commands/__init__.py
objectsyncer/management/commands/push_changes.py
objectsyncer/migrations/__init__.py
django_objectsyncer-1.0.1.dist-info/LICENSE
django_objectsyncer-1.0.1.dist-info/METADATA
django_objectsyncer-1.0.1.dist-info/WHEEL
django_objectsyncer-1.0.1.dist-info/top_level.txt
django_objectsyncer-1.0.1.dist-info/RECORD
