Metadata-Version: 2.1
Name: django-objectsyncer
Version: 1.0.1
Summary: A Django ObjectSyncer between a server and multiples clients
Home-page: https://github.com/mneitsabes/django-objectsyncer
Author: mneitsabes
Author-email: mneitsabes@nulloz.be
License: UNKNOWN
Keywords: django,object,sync
Platform: UNKNOWN
Classifier: Programming Language :: Python :: 3
Classifier: License :: OSI Approved :: MIT License
Classifier: Operating System :: OS Independent
Requires-Python: >=3.6
Requires-Dist: django
Requires-Dist: django-model-utils
Requires-Dist: requests
Requires-Dist: djangorestframework
